AUTHORS
LICENSE
MANIFEST.in
README.md
setup.py
thunderdome_logging/VERSION
thunderdome_logging/__init__.py
thunderdome_logging/graph_handler.py
thunderdome_logging/utils.py
thunderdome_logging.egg-info/PKG-INFO
thunderdome_logging.egg-info/SOURCES.txt
thunderdome_logging.egg-info/dependency_links.txt
thunderdome_logging.egg-info/requires.txt
thunderdome_logging.egg-info/top_level.txt