Metadata-Version: 1.0
Name: thunderdome-logging
Version: 1.0
Summary: Thunderdome graph error logging
Home-page: https://github.com/StartTheShift/thunderdome-logging
Author: StartTheShift
Author-email: dev@shift.com
License: BSD
Keywords: cassandra,titan,ogm,thunderdome,logging
Platform: UNKNOWN
Classifier: Development Status :: 3 - Alpha
Classifier: Environment :: Web Environment
Classifier: Environment :: Plugins
Classifier: License :: OSI Approved :: BSD License
Classifier: Operating System :: OS Independent
Classifier: Programming Language :: Python :: 2.6
Classifier: Programming Language :: Python :: 2.7
Classifier: Topic :: Internet :: WWW/HTTP
Classifier: Topic :: Software Development :: Libraries :: Python Modules
